./.gitignore
./LICENSE
./PKG-INFO
./README.md
./pyproject.toml
./supercollider_lexer.py
./supercollider_style.py
./tests/__init__.py
./tests/test_lexer.py
./tests/test_style_integration.py
pygments_supercollider_lexer-0.1.1.dist-info/METADATA
pygments_supercollider_lexer-0.1.1.dist-info/WHEEL
pygments_supercollider_lexer-0.1.1.dist-info/entry_points.txt
pygments_supercollider_lexer-0.1.1.dist-info/licenses/LICENSE
pygments_supercollider_lexer-0.1.1.dist-info/RECORD
