Metadata-Version: 2.4
Name: pygments-supercollider-lexer
Version: 0.1.1
Summary: A Pygments lexer for SuperCollider
Project-URL: Homepage, https://github.com/aeskildsen/pygments-supercollider-lexer
Project-URL: Repository, https://github.com/aeskildsen/pygments-supercollider-lexer
Project-URL: Issues, https://github.com/aeskildsen/pygments-supercollider-lexer/issues
Author: Anders Eskildsen
License-Expression: MIT
License-File: LICENSE
Keywords: pygments,supercollider,syntax highlighting
Classifier: Development Status :: 3 - Alpha
Classifier: Intended Audience :: Developers
Classifier: License :: OSI Approved :: MIT License
Classifier: Natural Language :: English
Classifier: Operating System :: OS Independent
Classifier: Programming Language :: Python :: 3
Classifier: Programming Language :: Python :: 3.8
Classifier: Programming Language :: Python :: 3.9
Classifier: Programming Language :: Python :: 3.10
Classifier: Programming Language :: Python :: 3.11
Classifier: Programming Language :: Python :: 3.12
Classifier: Topic :: Software Development :: Documentation
Classifier: Topic :: Software Development :: Libraries :: Python Modules
Classifier: Topic :: Text Processing :: Markup
Requires-Python: >=3.8
Requires-Dist: pygments>=2.19
Provides-Extra: dev
Requires-Dist: pytest>=7.0; extra == 'dev'
